lox_space-0.1.0a27.dist-info/METADATA
lox_space-0.1.0a27.dist-info/WHEEL
lox_space/__init__.py
lox_space/__init__.pyi
lox_space/lox_space.cp310-win_amd64.pyd
lox_space/py.typed
lox_space-0.1.0a27.dist-info/RECORD
