Metadata-Version: 2.4
Name: lox-space
Version: 0.1.0a27
Classifier: Programming Language :: Rust
Classifier: Programming Language :: Python :: Implementation :: CPython
Classifier: Programming Language :: Python :: Implementation :: PyPy
Requires-Dist: numpy>=1.16.0
Requires-Python: >=3.9
